MANIFEST.in
setup.py
examples/login.py
examples/login_web.py
familysearch/__init__.py
familysearch/authorities_v1.py
familysearch/familytree_v2.py
familysearch/identity_v2.py
familysearch/enunciate/__init__.py
familysearch/enunciate/identity.py
familysearch/tests/__init__.py
familysearch/tests/common.py
familysearch/tests/culture.json
familysearch/tests/culture_list.json
familysearch/tests/date.json
familysearch/tests/date_list.json
familysearch/tests/identity_properties.json
familysearch/tests/login.json
familysearch/tests/match.json
familysearch/tests/name.json
familysearch/tests/name_list.json
familysearch/tests/pedigree.json
familysearch/tests/pedigree_list.json
familysearch/tests/person1.json
familysearch/tests/person2.json
familysearch/tests/person_list.json
familysearch/tests/persona.json
familysearch/tests/persona_list.json
familysearch/tests/place.json
familysearch/tests/place_list.json
familysearch/tests/search.json
familysearch/tests/test_authorities.py
familysearch/tests/test_familysearch.py
familysearch/tests/test_familytree.py
familysearch/tests/test_identity.py
familysearch/tests/version.json
familysearch/tests/version_list.json
python_fs_stack.egg-info/PKG-INFO
python_fs_stack.egg-info/SOURCES.txt
python_fs_stack.egg-info/dependency_links.txt
python_fs_stack.egg-info/top_level.txt