Metadata-Version: 1.0
Name: python-fs-stack
Version: 0.2
Summary: Python wrapper for all FamilySearch APIs
Home-page: http://pypi.python.org/pypi/python-fs-stack
Author: Peter Henderson
Author-email: peterhenderson@byu.net
License: FamilySearch API License Agreement <https://devnet.familysearch.org/downloads/sample-code/sample-clients/sample-client-license>
Keywords: FamilySearch,genealogy,family history,API,OAuth,REST,JSON
Platform: UNKNOWN
Classifier: Development Status :: 4 - Beta
Classifier: Environment :: Console
Classifier: Environment :: No Input/Output (Daemon)
Classifier: Environment :: Web Environment
Classifier: Intended Audience :: Developers
Classifier: License :: Other/Proprietary License
Classifier: Operating System :: OS Independent
Classifier: Programming Language :: Python :: 2
Classifier: Topic :: Internet :: WWW/HTTP
Classifier: Topic :: Sociology :: Genealogy
Classifier: Topic :: Software Development :: Libraries :: Python Modules
